Workbook

Sheet Owner logic - current
A1: For owner/assignee on an elevation, what we need is to know who is actually working it, but for dealer community, they also have a backup contact that is added.
A3: Notes:
A4: This is current functionality, so SFDC handups are within Salesforce and being directly worked by the teams in SF. SFDC Handup ≠ SFDC Elevation (SFDC Elevation in MSD will be a new handup type)
A5: Manual Handups today are used for Dealer Resolution, Dealer Elevation and Email Handups
A6: Field | B6: Description
A7: Handup Owner | B7: SFDC: This is the person working the handup
B8: Manual/SNOW: This is the person who opened the handup (not relevant)
A9: Assignment Group | B9: Team working the case (different assignment group tables per handup type)
A10: Assignee | B10: Manual Only: This is a contact lookup field. If the handup partner is not a contact, we can't use this field (assignee or assignee email are required- one, not both)
A11: Assignee Email | B11: Manual Only: Email Address of the primary handup contact
A12: Assignee Name | B12: Manual Only: Name of primary handup contact
A13: Additional Email | B13: Manual Only: Email Address of secondary handup contact (used on dealer resolution handups)
A14: Additional Name | B14: Manual Only: Name of secondary handup contact (used on dealer resolution handups)

Sheet D365-ServiceNow
A1: Field | B1: Field Type | C1: Notes | D1: D365 Schema Field | E1: ServiceNow Field | F1: SNOW - Format (if Any) | G1: SNOW - Default Value (IF any)
A2: Subject | B2: Text | D2: title
A3: Service Type | B3: Picklist | C3: Service Request Incident | D3: cat_servicetype
A4: Service | B4: Lookup | C4: Sync'd from ServiceNow | D4: cat_serivce | E4: business_service
A5: Assignment Group | B5: Lookup | D5: cat_assignmentgroupid | E5: assignment_group
A6: Priority | B6: Picklist | C6: Automated - matches parent case, but can be changed | D6: prioritycode | E6: priority | G6: 4
A7: Status | B7: Text | C7: Automated | D7: statecode | E7: state | G7: 1
A8: Description | B8: Text | D8: description | E8: description
A9: Handup Reason
A10: Tracking Number | D10: cat_trackingnumber
A11: External Link | D11: cat_externallink
A12: Integration Error Message | D12: cat_integrationerrormessage
A13: Skip Integration Re-Process | B13: Checkbox | D13: cat_skipintegrationreprocess
A14: Integrated Ticket Status | B14: Lookup | C14: Populates the status of the Handup from the integrated system | D14: cat_integratedticketstatus
A15: Skip Support Ticket | B15: Checkbox | D15: cat_skipsupportticket
A16: Resolution Notes | B16: Text | D16: cat_caseresolutionnote | E16: close_notes
A17: Attachments / Files
A18: Handup Age | B18: Calculated Field | D18: caseage
A19: Handup SLA | B19: Calculated Field | C19: Not a field we have today but SLA for Handup is different than the case age. Let's discuss | D19: No Field in D365 Case Entity
A20: Handup Type | B20: Option | D20: cat_elevationtype
A21: Created By | B21: Lookup | C21: Automated | D21: createdby | E21: sys_created_by
A22: Last Modified By | B22: Lookup | C22: Automated | D22: modifiedby | E22: sys_updated_by
A23: Contact Name | B23: Text | D23: cat_contactname
A24: Contact | B24: Lookup for Contact Entity | D24: primarycontactid
A25: Contact Phone Number | B25: Phone Number | C25: Contact Entity | D25: address1_telephone1
A26: Contact Email Address | B26: email | C26: Contact Entity | D26: emailaddress1
A27: Machine/Asset | B27: Text | D27: cat_machine
A28: Machine S/N | B28: Text | D28: cat_machinesn
A29: Dealer / Dealer Code | B29: Text | D29: cat_dealercode
A30: Dealer Resolution | B30: Multi Line Text | D30: cat_dealerresolution
A31: Product Technology | B31: Look Up | C31: (from case) | D31: productid
A32: Handup ID | B32: Text | C32: (Handup name) | D32: cat_elevationid
A33: Case Number (Hand Number) | B33: Auto Number | C33: (original/parent case) | D33: ticketnumber | E33: correlation_display
A34: Handup Owner | D34: ownerid
A35: Contact City | B35: Text | C35: Contact Entity | D35: address1_city
A36: Contact State | B36: Text | C36: Contact Entity | D36: address1_stateorprovince
A37: Zip Code | B37: Text | C37: Contact Entity | D37: address1_postalcode
A38: Assignee Email | B38: Email | D38: cat_assigneeemail
A39: Assignee Name | B39: Text | D39: cat_assigneename | E39: assigned_to
A40: Additional Assignee | B40: Text | D40: cat_additionalassigneename
A41: Additional Email | B41: email | D41: cat_additionalassigneeemail
A42: Handup Assignee | B42: Look Up | D42: cat_handupassignee
A43: Action Requested | B43: Multi Line Text | D43: cat_actionrequested
A44: Approval Handup | B44: Checkbox | C44: Advisors can check when it's a simple approval handup to allow consistent metrics across resolution tiers | D44: No Field in D365 Case Entity
A47: ServiceNow Contacts: | B47: Matt Kean | C47: Rachel (last name)
A48: Field | B48: Field Type | C48: Notes | D48: ServiceNow | E48: ServiceNow Field schema name - Incident | F48: ServiceNow Feild schema name - Service Request | G48: Notes
A49: Subject | B49: Text | D49: Required
A50: Service Type | B50: Picklist | C50: Service Request Incident(mapping needs to be checked for service request in snow) | D50: Required
A51: Service | B51: Lookup | C51: Sync'd from ServiceNow | D51: Required | E51: business_service | F51: business_service (sc_task)
A52: Assignment Group | B52: Lookup | C52: Required - advisor will select it manually just for tracking purpose. These assignement groups will be added manually | D52: Required | E52: assignment_group | F52: assignment_group(sc_task)
A53: Priority | B53: Picklist | C53: Automated - matches parent case, but can be changed | D53: Required | E53: priority | F53: priority | G53: update on both sc_task & sc_req_item
A54: Status | B54: Picklist | C54: Automated / Manual | D54: Not Sync'd (both are new upon creation) | E54: state | F54: State(sc_task) | G54: sc_task
A55: Description | B55: Text | D55: Required - Creation | E55: description | F55: description(sc_task)
A56: Tracking Number | D56: From SNOW > MSD
A57: External Link | C57: On SNOW- Field not require just a link at servicenow that will be sent to D365 | D57: From SNOW > MSD | E57: Field not required | F57: Field not required
A58: Integration Error Message | C58: On Snow : Field not required | D58: Not Sync'd | E58: Field not required | F58: Field not required
A59: Skip Integration Re-Process | B59: Checkbox | C59: On Snow : Require new field | D59: Not Sync'd | F59: check for existing field
A60: Integrated Ticket Status | B60: Text | C60: Populates the incident state of the Handup from the integrated system (need to confirm the choices of state from saurabh) | D60: From SNOW > MSD | E60: State | F60: State(sc_task)
A61: Skip Support Ticket | B61: Checkbox | C61: On Snow : no field required | D61: Not Sync'd | E61: Field not required | F61: Field not required
A62: Resolution Notes | B62: Text | C62: On Snow : OOTB | D62: Required to Close (copy and append Resolution from SNOW) | E62: close_notes | F62: Not needed
A63: Attachments / Files | D63: Optional - sync'd between systems | F63: To be checked with Matt
A64: Handup Age | B64: Calculated Field | C64: Calculated field from D365 as part of the description | D64: Not Sync'd | F64: Not needed
A65: Handup SLA | B65: Calculated Field | C65: Not a field we have today but SLA for Handup is different than the case age. Let's discuss | D65: Prefix of EVERY comment(description field in snow) from MSD > SNOW | E65: description | F65: Not needed
A66: Handup Type | B66: Option | C66: Field not required in Snow | D66: Not Sync'd | F66: Field not required
A67: Created By | C67: On Snow : OOTB | D67: Not Sync'd | F67: On Snow : OOTB
A68: Last Modified By | C68: On Snow : OOTB | D68: Not Sync'd | F68: On Snow : OOTB
A69: Product Technology | C69: On Snow : in short description | D69: Not Sync'd | E69: short_description | F69: Not needed
A70: Handup Number | C70: On Snow : in short description coming from D365 | D70: Prefix of Subject/Title | E70: short_description | F70: short_description(sc_task)
A71: Case Number | C71: (original/parent case) | D71: Prefix of Subject/Title
A72: Handup Owner | C72: On Snow : Field not required | D72: Not Sync'd | F72: Not needed
A73: Approval Handup | B73: Checkbox | C73: Advisors can check when it's a simple approval handup to allow consistent metrics across resolution tiers | D73: Not Sync'd
A77: ServiceNow Timeline:
A78: Code Freeze: | B78: QA/Business Signoff | C78: Production Date
A79: (All code in lower env) | B79: (All testing complete)
A80: 46307 | B80: 46310 | C80: 46319
A81: 46335 | B81: 46338 | C81: 46347
A82: 46363 | B82: 46366 | C82: 46375

Sheet Fields by Type
A1: Field | B1: Field Type | C1: Notes | D1: Manual | E1: Dynamics | F1: Dealer Customer Resolution | G1: Dealer Consulation | H1: ServiceNow | I1: Salesforce | J1: HC Visibility (for Dealer Handups only) | K1: D365 Field | L1: Clarification required
A2: Subject | B2: Text | D2: (Required on Email) | F2: - | G2: - | H2: Required | I2: Required (maps to title) | J2: Yes | K2: OOTB | L2: subject
A3: Service Type | B3: Picklist | C3: Service Request Incident | D3: NA | E3: NA | F3: NA | G3: NA | H3: Required | I3: NA | K3: Custom | L3: Request picklist values? 7/7/2026 (POD 1): Handup Type is equal to Service Type? if different then type of Service Type?
A4: Service | B4: Lookup | C4: Sync'd from ServiceNow | D4: NA | E4: NA | F4: NA | G4: NA | H4: Required | I4: NA | K4: Custom? | L4: Lookup to which object/entity? i.e. 11541 Data migration team will handle 7/2/2026 (business ): Service is the platform, service, UI, system, etc. and assignment group is the team working it. Only service now has assignment group and service ). For sfdc there is just 1 assignment group
A5: Assignment Group | B5: Lookup | C5: Required - advisor will select it manually just for tracking purpose. These assignement groups will be added manually | D5: Required - advisor will select it manually just for tracking purpose. These assignement groups will be added manually | E5: Required - advisor will select it manually just for tracking purpose | F5: Required | G5: Required | H5: Required | I5: Required | L5: Lookup to which object/entity? Data migration team will handle. Lookup to the team. Assignment group is used only in service now . SFDC will have just 1 AG- will pull from a different table.(dealer collaboration community team)
A6: Priority | B6: Picklist | C6: Automated - matches parent case, but can be changed. Apply to all handup type | D6: Required | E6: Required | F6: Automated and Required | G6: Automated and Required | H6: Required | I6: Required | K6: OOTB | L6: OOTB Values
A7: Status | B7: Picklist | C7: Automated / Manual - Default as "New" | D7: Required- Default as New | E7: Required | F7: Required | G7: Required | H7: Required | I7: Required | J7: Yes | K7: OOTB | L7: status - values coming from SNOW or SFDC . Can be a text field
A8: Description | B8: Text | C8: description will be entered manually be advisors | D8: Required | E8: Required | F8: Required | G8: Required | H8: Required | I8: Required | J8: Yes | K8: OOTB | L8: description
A9: External Link | C9: URL to snow and Salesforce tickets. NA for others | D9: No | E9: No | F9: NA | G9: NA | H9: Automated | I9: Automated | K9: Custom | L9: URL? should we open on click
A10: Integration Error Message | D10: No | E10: No | F10: NA | G10: NA | H10: Automated | I10: Automated | K10: Custom?
A11: Skip Integration Re-Process | B11: Checkbox | D11: No | E11: No | F11: NA | G11: NA | H11: Automated (can be manually unchecked) | I11: Automated | K11: Custom | L11: Request the details on automated process as it is checkbox. This and previous field used to to send back or not if a error happens in integration EX: assignment group reassigned - SC can you build on this
A12: Integrated Ticket Status | B12: Lookup text | C12: SNOW or CRMi Status . Populates the status of the Handup from the integrated system | D12: No | E12: No | F12: NA | G12: NA | H12: Automated | I12: Automated | K12: Custom? | L12: What will be the values? Since it is lookup field which object / entity to look for? If automated, cant we keep it a text field? This field holds Status on service now and SFDC. Will be a text field . Can be used to mark Handup as resolved. If resolved by dealer then status on child case = Resolved By Dealer For everyone else it is resolution Provided. 7/7/2026 (POD 1): we have made it as choice (Yes/No), if not this then what will be the other values for choice?
A13: Skip Support Ticket | B13: Checkbox | C13: associated with error processing . can be used by new integration (if needed) to trigger manual action . It will alert the dev team | D13: No | E13: No | F13: NA | G13: NA | H13: Automated | I13: Automated | K13: Custom | L13: Purpose? What is the logic of automation? If an error happens this field can be used to manully retrigger the process. Dependent on the final solution cap team builds.
A14: Resolution Notes | B14: Text | D14: Required to close | E14: Required to close | F14: Required to Close | G14: Required to close | H14: Required to Close (copy and append Resolution from SNOW) | J14: On Resolution Details Tab | L14: text field holding the description of the resolution in SFDC or SNOW /Manual . Editable for all , notes from sfdc, snow gets appended to the current comments
A15: Attachments / Files | C15: If there are attachments on case then advisor can pick one or more attachment and copy that to the child handup. This is a manual action. Custom solution was built to enable this feature | D15: Optional | E15: Optional | F15: Optional | G15: Optional | H15: Optional - sync'd between systems | I15: Optional - sync'd between systems | K15: Notes
A16: Handup Age | B16: Calculated Field | C16: Does not gets carried over from parent case. Handup age is a field on the handup/child case record | D16: Automated | E16: Automated | F16: Automated | G16: Automated | H16: Automated | I16: Automated | K16: OOTB | L16: Case Age ( open to close )
A17: Handup Case SLA | B17: Calculated Field | C17: Show the SLA running at the parent case . May throw technical challenge. need to investigate. Can we use copilot to show the latest case SLA | D17: Automated | E17: Automated | F17: Automated | G17: Automated | H17: Automated | I17: Automated | K17: ? | L17: exclude certain statuses and calcualte teht ime spent on the Handup
A18: Handup Type | B18: Option | C18: as shown on header row | D18: Automated | E18: Automated | F18: Automated | G18: Automated | H18: Automated | I18: Automated | K18: Custom? | L18: Values? Manual. SFDC. SNOW How it is being updates
A19: Created By | C19: deafulted to the user who creates the hanup | D19: Automated | E19: Automated | F19: Automated | G19: Automated | H19: Automated | I19: Automated | L19: OOTB field
A20: Last Modified By | C20: Automated | D20: Automated | E20: Automated | F20: Automated | G20: Automated | H20: Automated | I20: Automated | L20: OOTB field
A21: Contact Name | D21: No | E21: No | F21: Automated from Case if Customer Persona | G21: Automated from Case if Customer Persona Do not display on Dealer/Internal Persona | H21: No | I21: No | J21: Customer Requester Only | L21: Related to Contact record. Populate from Requested For if there is a contact else populate it from requested by - fields 24 - 26) 7/7/2026 (POD 1): This field is being mapped to contact entity and we do not plan to create a seperate field for it, is it acceptable or do you require us to create this field?
A22: Contact Phone Number | D22: No | E22: No | F22: Automated from Case if Customer Persona | G22: Automated from Case if Customer Persona Do not display on Dealer/Internal Persona | H22: No | I22: No | J22: Customer Requester Only | L22: Related to Contact record 7/7/2026 (POD 1): This field is being mapped to contact entity and we do not plan to create a seperate field for it, is it acceptable or do you require us to create this field?
A23: Contact Email Address | D23: No | E23: No | F23: Automated from Case if Customer Persona | G23: Automated from Case if Customer Persona Do not display on Dealer/Internal Persona | H23: No | I23: No | J23: Customer Requester Only | L23: Related to Contact record 7/7/2026 (POD 1): This field is being mapped to contact entity and we do not plan to create a seperate field for it, is it acceptable or do you require us to create this field?
A24: Machine/Asset | D24: No | E24: No | F24: Automated from Case if Customer Persona | G24: Automated from Case if Customer Persona Do not display on Dealer/Internal Persona | H24: No | I24: No | L24: Will it come from Case or Asset? If Asset in case of multi asset scenario, how will this work? 7/7/2026 (POD 1): These are two different fields? and what are the type of Machine and Asset field?
A25: Machine S/N | D25: No | E25: No | F25: Automated from Case if Customer Persona | G25: Automated from Case if Customer Persona Do not display on Dealer/Internal Persona | H25: No | I25: No | L25: Will it come from Case or Asset? If Asset in case of multi asset scenario, how will this work? 7/7/2026 (POD 1):What is Machine S/N Type?
A26: Dealer / Dealer Code | D26: No | E26: No | F26: Automated from Case if Customer Persona else will be filled in manually by advisor | G26: Lookup | H26: No | I26: No | J26: Yes
A27: Dealer Resolution | D27: No | E27: No | F27: Required to Close | G27: No | H27: No | I27: No
A28: Product Technology | C28: (from case)- just the product technology | D28: Automated | E28: Automated | F28: Automated | G28: Automated | H28: Automated | I28: Automated | J28: Yes
A29: Handup ID Number | C29: (Handup name) - OOB case number :case/hanup number . generates automatically. Will be send to service now and salesforce appended in text . This field will be used on email subject line | D29: Automated | E29: Automated | F29: Automated | G29: Automated | H29: Automated | I29: Automated | J29: Yes | K29: Custom | L29: Request if any specific format to be followed? Unique child case / Handup number 7/7/2026 (POD 1): Is Case Number and Handup ID same?
A30: Parent Case Number | C30: (original/parent case) | D30: Automated | E30: Automated | F30: Automated | G30: Automated | H30: Automated | I30: Automated | K30: OOTB | L30: Format will be same as original Case?actual case that was submitted . parent case number . starts with TST , ahndup starts with different prefix
A31: Handup Owner | C31: Only Dynamics Handup Type will be sent to queue to be picked by the teams . Manual handup will not be sent to queue. Dealer Consultation ,Dealer Customer resolution- stays with the person who created the handup. Does not go to queue. Service Now /Salesforce - stays with the person who created it | D31: Automated | E31: Automated | F31: Automated | G31: Automated | H31: Automated | I31: Automated | J31: Yes | K31: OOTB | L31: Owner. Will this be case Owner or New owner to which Handup assigned to?
A32: Contact City | D32: No | E32: No | F32: Automated from Case if Customer Persona | G32: Automated from Case if Customer Persona Do not display on Dealer/Internal Persona | H32: No | I32: No | J32: Customer Requester Only | L32: Related to Contact record
A33: Contact State | D33: No | E33: No | F33: Automated from Case if Customer Persona | G33: Automated from Case if Customer Persona Do not display on Dealer/Internal Persona | H33: No | I33: No | J33: Customer Requester Only | L33: Related to Contact record
A34: Zip Code | D34: No | E34: No | F34: Automated from Case if Customer Persona | G34: Automated from Case if Customer Persona Do not display on Dealer/Internal Persona | H34: No | I34: No | J34: Customer Requester Only | L34: Related to Contact record
A35: Assignee Email | D35: Required | E35: No | F35: Required | G35: Required | J35: Yes | K35: Custom | L35: Do we need the field. 7/14/2026 (Saurabh) - yes we need this field to be created locally in dynamics. If there is any notification we will be using the email popualted on field to send the notification.
A36: Assignee Name | B36: Text | D36: Required | E36: No | F36: Required | G36: Required
A37: Additional Assignee | D37: Optional | E37: No | F37: Optional | G37: Optional | J37: Yes | L37: 8/7/2026 (POD 1): Is "Assignee to other" and Assignee Email same?
A38: Additional Email | D38: Optional | E38: No | F38: Optional | G38: Optional | J38: Yes | K38: Custom | L38: 7/7/2026 (POD 1): Additional email 1 and Additional email 2 is available in case, do you want us to create new field 'Additional email' ?
A39: Handup Assignee | F39: Lookup | G39: Lookup - Contact Record | J39: Yes | L39: How it is different than Owner? It will be a lookup to user? 7/7/2026 (POD 1): Handup owner and Handup Assignee are different field? 7/9/2026 - Saurabh - Handup Owner is the Internal Dynamcis User whereas Handup Assignee is the contact lookup . When discussing contact repo solution can we find a way to bring in the contacts easily from helios . Dealers will be using this field to internally reassign the Handup to a different user from their dealership (from tiffani) Manual Only: This is a contact lookup field. If the handup partner is not a contact, we can't use this field (assignee or assignee email are required- one, not both)
A40: Action Requested | B40: Text | F40: Required | G40: Required | J40: Yes | L40: What is the data type? 7/7/2026 (POD 1): Need Optionset value for Action Requested
A41: Approval Handup | B41: Checkbox | C41: Advisors can check when it's a simple approval handup to allow consistent metrics across resolution tiers. On portal it controls the dealer status ( to be covererd on portal status) | D41: Optional | E41: Optional | F41: N/A | G41: Optional | H41: Optional | I41: Optional | J41: No | K41: No
A58: HANDUP TITLES:
A59: Handup Number
A60: Case Number
A61: Status
A62: Priority
A63: Tracking Number
A64: External Link
A65: Contact Name
A67: Assigneed User
A68: Contact City

Sheet SF to D365 Handup Types
A1: Current | B1: Future | C1: Assignment Group | D1: Notes
A2: Manual | B2: Manual | C2: Not = Dealer Group
A3: Manual | B3: Dealer Consulation | C3: Dealer Group | D3: Non-eComm Case
A4: Manual | B4: Dealer Customer Resolution | C4: Dealer Group | D4: eCommerce Case
A5: SFDC | B5: Dynamics | C5: Not = Dealer Collaboration Tier 2 Group
A6: SFDC | B6: Salesforce | C6: Dealer Collaboration Tier 2 Group
A7: ServiceNow | B7: ServiceNow

Sheet Assignment Groups - Int & Ext
A1: SF Assignment Group Type | B1: SF Assignment Group Name | C1: Create? | D1: SE | E1: D365 Assignment Group Type | F1: D365 Assignment Group Name | G1: Notes | H1: Column1 | J1: Note: ServiceNow Assignment Groups will sync through the integration | L1: Refer to SF to D365 Handup Types | P1: KPM send no's to Hari - "no recreate"
A2: SFDC Handup | B2: Cat Rental Tier 2 Group | C2: No | D2: Stacy / Julia | E2: X | F2: Retired | G2: Check with Stacy and Julia | H2: =IFERROR(VLOOKUP(Table3[[#This Row],[SF Assignment Group Name]],'Assignment Group Usage'!B:D,3,FALSE),0) -> 22
A3: SFDC Handup | B3: DMT Approval Group | C3: No | E3: X | F3: Retired | G3: Internal Process - DMT retired for CCID management | H3: =IFERROR(VLOOKUP(Table3[[#This Row],[SF Assignment Group Name]],'Assignment Group Usage'!B:D,3,FALSE),0) -> 1
A4: SFDC Handup | B4: CCS SOS T2 Group | C4: No | E4: X | F4: Retired | G4: No longer used | H4: =IFERROR(VLOOKUP(Table3[[#This Row],[SF Assignment Group Name]],'Assignment Group Usage'!B:D,3,FALSE),0) -> 13
A5: SFDC Handup | B5: eCommerce Dealer Escalation Group | C5: No | E5: X | F5: Retired | G5: Not used in 2026. | H5: =IFERROR(VLOOKUP(Table3[[#This Row],[SF Assignment Group Name]],'Assignment Group Usage'!B:D,3,FALSE),0) -> 17
A6: Manual Handup | B6: Managed Account Group | C6: No | E6: X | F6: Retired | G6: Not used in 2026. | H6: =IFERROR(VLOOKUP(Table3[[#This Row],[SF Assignment Group Name]],'Assignment Group Usage'!B:D,3,FALSE),0) -> 11
A7: SFDC Handup | B7: Data Product Mgmt T2 Group | C7: No | E7: X | F7: Retired | G7: Not used in 2026. | H7: =IFERROR(VLOOKUP(Table3[[#This Row],[SF Assignment Group Name]],'Assignment Group Usage'!B:D,3,FALSE),0) -> 10
A8: SFDC Handup | B8: Foresight CM Group | C8: No | E8: X | F8: Retired | G8: Not used in 2026. | H8: =IFERROR(VLOOKUP(Table3[[#This Row],[SF Assignment Group Name]],'Assignment Group Usage'!B:D,3,FALSE),0) -> 3
A9: Manual Handup | B9: EU Data Group | C9: No | E9: X | F9: Retired | G9: Not used in 2026. | H9: =IFERROR(VLOOKUP(Table3[[#This Row],[SF Assignment Group Name]],'Assignment Group Usage'!B:D,3,FALSE),0) -> 2
A10: Manual Handup | B10: BaaS Tier 2 Group | C10: No | E10: X | F10: Retired | G10: Not used in 2026. | H10: =IFERROR(VLOOKUP(Table3[[#This Row],[SF Assignment Group Name]],'Assignment Group Usage'!B:D,3,FALSE),0) -> 1
A11: Manual Handup | B11: Cat Inspect API Approval Group | C11: No | E11: X | F11: Retired | G11: Not used in 2026. | H11: =IFERROR(VLOOKUP(Table3[[#This Row],[SF Assignment Group Name]],'Assignment Group Usage'!B:D,3,FALSE),0) -> 1
A12: SFDC Handup | B12: Cat Technology Monitoring Group | C12: No | E12: X | F12: Retired | G12: Not used in 2026. | H12: =IFERROR(VLOOKUP(Table3[[#This Row],[SF Assignment Group Name]],'Assignment Group Usage'!B:D,3,FALSE),0) -> 1
A13: Manual Handup | B13: Manual Test Record | C13: No | E13: X | F13: Retired | G13: Not used in 2026. | H13: =IFERROR(VLOOKUP(Table3[[#This Row],[SF Assignment Group Name]],'Assignment Group Usage'!B:D,3,FALSE),0) -> 1
A14: Manual Handup | B14: Mining | C14: No | E14: X | F14: Retired | G14: Not used in 2026. | H14: =IFERROR(VLOOKUP(Table3[[#This Row],[SF Assignment Group Name]],'Assignment Group Usage'!B:D,3,FALSE),0) -> 1
... A69: Manual Handup | B69: Dealer Services Group | C69: No | E69: X | F69: Retired | G69: Transferred to SFDC group | H69: =IFERROR(VLOOKUP(Table3[[#This Row],[SF Assignment Group Name]],'Assignment Group Usage'!B:D,3,FALSE),0) -> 2
A70: SFDC Handup | B70: Soft Blocks Group | C70: No | E70: X | F70: Retired | H70: =IFERROR(VLOOKUP(Table3[[#This Row],[SF Assignment Group Name]],'Assignment Group Usage'!B:D,3,FALSE),0) -> 626
A71: Manual Handup | B71: Dealer Collaboration Community Group | C71: No | D71: Kath | E71: X | F71: Retired | H71: =IFERROR(VLOOKUP(Table3[[#This Row],[SF Assignment Group Name]],'Assignment Group Usage'!B:D,3,FALSE),0) -> 25
A72: Manual Handup | B72: Cat Central Group | C72: No | E72: X | F72: Retired | H72: =IFERROR(VLOOKUP(Table3[[#This Row],[SF Assignment Group Name]],'Assignment Group Usage'!B:D,3,FALSE),0) -> 1
A73: Manual Handup | B73: DSP Group | C73: No | E73: X | F73: Retired | H73: =IFERROR(VLOOKUP(Table3[[#This Row],[SF Assignment Group Name]],'Assignment Group Usage'!B:D,3,FALSE),0) -> 1
A74: Manual Handup | B74: Specsizer Group | C74: No | D74: Carita / Lauren | F74: Retired | H74: =IFERROR(VLOOKUP(Table3[[#This Row],[SF Assignment Group Name]],'Assignment Group Usage'!B:D,3,FALSE),0) -> 24
A75: Manual Handup | B75: VST Group | C75: No | D75: Carita / Lauren | F75: Retired | G75: Ask Carita and Lauren | H75: =IFERROR(VLOOKUP(Table3[[#This Row],[SF Assignment Group Name]],'Assignment Group Usage'!B:D,3,FALSE),0) -> 1
A76: Manual Handup | B76: Cat Inspect Group | C76: No | D76: Kath | F76: Retired | H76: =IFERROR(VLOOKUP(Table3[[#This Row],[SF Assignment Group Name]],'Assignment Group Usage'!B:D,3,FALSE),0) -> 1
C77: Yes | D77: Kath / Lauren | E77: Dynamics | F77: ACE | G77: new handup for ace.cat.com | H77: =IFERROR(VLOOKUP(Table3[[#This Row],[SF Assignment Group Name]],'Assignment Group Usage'!B:D,3,FALSE),0) -> 0
A78: Manual Handup | B78: API Group | C78: Yes | D78: Lauren | E78: Manual | F78: API | H78: =IFERROR(VLOOKUP(Table3[[#This Row],[SF Assignment Group Name]],'Assignment Group Usage'!B:D,3,FALSE),0) -> 7
A79: Manual Handup | B79: Billing Group | C79: Yes | D79: Mike | E79: Manual | F79: Billing T2 | H79: =IFERROR(VLOOKUP(Table3[[#This Row],[SF Assignment Group Name]],'Assignment Group Usage'!B:D,3,FALSE),0) -> 14
A80: Manual Handup | B80: Bulk CCID Creation Group | C80: Yes | D80: Mike | E80: Manual | F80: Bulk CCID Creation | H80: =IFERROR(VLOOKUP(Table3[[#This Row],[SF Assignment Group Name]],'Assignment Group Usage'!B:D,3,FALSE),0) -> 3
A81: SFDC Handup | B81: CAIT: Harvester Tier 2 | C81: Yes | D81: Lauren | E81: Dynamics | F81: CAIT: Harvester T2 | H81: =IFERROR(VLOOKUP(Table3[[#This Row],[SF Assignment Group Name]],'Assignment Group Usage'!B:D,3,FALSE),0) -> 36
A82: SFDC Handup | B82: Cat Central Group | C82: Yes | E82: Dynamics | F82: Cat Central | H82: =IFERROR(VLOOKUP(Table3[[#This Row],[SF Assignment Group Name]],'Assignment Group Usage'!B:D,3,FALSE),0) -> 1
A83: SFDC Handup | B83: Cat Converge - Accenture SI Group | C83: Yes | D83: Luke | E83: Dynamics | F83: Cat Converge - Accenture SI | H83: =IFERROR(VLOOKUP(Table3[[#This Row],[SF Assignment Group Name]],'Assignment Group Usage'!B:D,3,FALSE),0) -> 2
A84: Manual Handup | B84: Cat Foresight Group | C84: Yes | D84: Kath | E84: Manual | F84: Cat Foresight | H84: =IFERROR(VLOOKUP(Table3[[#This Row],[SF Assignment Group Name]],'Assignment Group Usage'!B:D,3,FALSE),0) -> 88
A85: SFDC Handup | B85: Analytics Group | C85: Yes | D85: Darlene | E85: Dynamics | F85: CCS DAS Analytics | G85: (Tiffani Renamed) | H85: =IFERROR(VLOOKUP(Table3[[#This Row],[SF Assignment Group Name]],'Assignment Group Usage'!B:D,3,FALSE),0) -> 22
A86: SFDC Handup | B86: CCS Dealer Services Group | C86: Yes | E86: Dynamics | F86: CCS Dealer Services | H86: =IFERROR(VLOOKUP(Table3[[#This Row],[SF Assignment Group Name]],'Assignment Group Usage'!B:D,3,FALSE),0) -> 8
A87: SFDC Handup | B87: CI Tech T2 Group | C87: Yes | E87: Dynamics | F87: CI Tech T2 | H87: =IFERROR(VLOOKUP(Table3[[#This Row],[SF Assignment Group Name]],'Assignment Group Usage'!B:D,3,FALSE),0) -> 1
A88: SFDC Handup | B88: CSO Group | C88: Yes | D88: Mike | E88: Dynamics | F88: CSO | H88: =IFERROR(VLOOKUP(Table3[[#This Row],[SF Assignment Group Name]],'Assignment Group Usage'!B:D,3,FALSE),0) -> 30
A89: SFDC Handup | B89: Customer Admin Tool T2 Group | C89: Yes | D89: Mike | E89: Dynamics | F89: Customer Admin Tool T2 | H89: =IFERROR(VLOOKUP(Table3[[#This Row],[SF Assignment Group Name]],'Assignment Group Usage'!B:D,3,FALSE),0) -> 167
A90: SFDC Handup | B90: DDC Group | C90: Yes | D90: Mike | E90: Dynamics | F90: DDC | H90: =IFERROR(VLOOKUP(Table3[[#This Row],[SF Assignment Group Name]],'Assignment Group Usage'!B:D,3,FALSE),0) -> 27
A91: SFDC Handup | B91: Dealer Collaboration Tier 2 Group | C91: Yes | D91: Kath | E91: Salesforce | F91: Dealer Collaboration T2 | G91: Will remain on SF and worked through integration | H91: =IFERROR(VLOOKUP(Table3[[#This Row],[SF Assignment Group Name]],'Assignment Group Usage'!B:D,3,FALSE),0) -> 123
A92: Manual Handup | B92: Dealer Group | C92: Yes | D92: Kath | E92: Dealer Handup | F92: Dealer Group | H92: =IFERROR(VLOOKUP(Table3[[#This Row],[SF Assignment Group Name]],'Assignment Group Usage'!B:D,3,FALSE),0) -> 1642
A93: SFDC Handup | B93: DGS Group | C93: Yes | D93: Mike | E93: Dynamics | F93: DGS | H93: =IFERROR(VLOOKUP(Table3[[#This Row],[SF Assignment Group Name]],'Assignment Group Usage'!B:D,3,FALSE),0) -> 8
A94: SFDC Handup | B94: Digital Billing Tier 2 Group | C94: Yes | D94: Mike | E94: Dynamics | F94: Digital Billing T2 | H94: =IFERROR(VLOOKUP(Table3[[#This Row],[SF Assignment Group Name]],'Assignment Group Usage'!B:D,3,FALSE),0) -> 33
A95: SFDC Handup | B95: DNA Product Group | C95: Yes | D95: Kath | F95: DNA Product | H95: =IFERROR(VLOOKUP(Table3[[#This Row],[SF Assignment Group Name]],'Assignment Group Usage'!B:D,3,FALSE),0) -> 2
A96: SFDC Handup | B96: DSP/PMM Group | C96: Yes | D96: Mike | E96: Dynamics | F96: DSP/PMM | H96: =IFERROR(VLOOKUP(Table3[[#This Row],[SF Assignment Group Name]],'Assignment Group Usage'!B:D,3,FALSE),0) -> 468
A97: SFDC Handup | B97: Foresight CVA Group | C97: Yes | D97: Kath | E97: Dynamics | F97: Foresight CVA | H97: =IFERROR(VLOOKUP(Table3[[#This Row],[SF Assignment Group Name]],'Assignment Group Usage'!B:D,3,FALSE),0) -> 44
A98: SFDC Handup | B98: Foresight PM Group | C98: Yes | D98: Kath | E98: Dynamics | F98: Foresight PM | H98: =IFERROR(VLOOKUP(Table3[[#This Row],[SF Assignment Group Name]],'Assignment Group Usage'!B:D,3,FALSE),0) -> 26
A99: SFDC Handup | B99: FOTA Group | C99: Yes | D99: Jason | E99: Dynamics | F99: FOTA | H99: =IFERROR(VLOOKUP(Table3[[#This Row],[SF Assignment Group Name]],'Assignment Group Usage'!B:D,3,FALSE),0) -> 90
A100: SFDC Handup | B100: Insights Hub Group | C100: Yes | D100: Mike | E100: Dynamics | F100: Insights Hub T2 | H100: =IFERROR(VLOOKUP(Table3[[#This Row],[SF Assignment Group Name]],'Assignment Group Usage'!B:D,3,FALSE),0) -> 54
A101: SFDC Handup | B101: OLGA Product Group | C101: Yes | D101: Kath | E101: Dynamics | F101: OLGA Product | H101: =IFERROR(VLOOKUP(Table3[[#This Row],[SF Assignment Group Name]],'Assignment Group Usage'!B:D,3,FALSE),0) -> 1
A102: SFDC Handup | B102: Onboard Engineering Group | C102: Yes | D102: Lauren | E102: Dynamics | F102: Onboard Engineering | H102: =IFERROR(VLOOKUP(Table3[[#This Row],[SF Assignment Group Name]],'Assignment Group Usage'!B:D,3,FALSE),0) -> 1
A103: SFDC Handup | B103: PACs ADSD Group | C103: Yes | D103: Kath | E103: Dynamics | F103: PACs ADSD Group | H103: =IFERROR(VLOOKUP(Table3[[#This Row],[SF Assignment Group Name]],'Assignment Group Usage'!B:D,3,FALSE),0) -> 1
A104: SFDC Handup | B104: PACs APD Group | C104: Yes | D104: Kath | E104: Dynamics | F104: PACs APD Group | H104: =IFERROR(VLOOKUP(Table3[[#This Row],[SF Assignment Group Name]],'Assignment Group Usage'!B:D,3,FALSE),0) -> 1
A105: SFDC Handup | B105: PACs EAME Group | C105: Yes | D105: Kath | F105: PACs EAME | H105: =IFERROR(VLOOKUP(Table3[[#This Row],[SF Assignment Group Name]],'Assignment Group Usage'!B:D,3,FALSE),0) -> 2
A106: Manual Handup | B106: eCommerce Group | C106: Yes | E106: Manual | F106: Parts & Service | G106: Non-SF/ Dynamics handup partners, ex. Cat-Fi Used, EPVIP, Finance | H106: =IFERROR(VLOOKUP(Table3[[#This Row],[SF Assignment Group Name]],'Assignment Group Usage'!B:D,3,FALSE),0) -> 24
A107: SFDC Handup | B107: PST Group China | C107: Yes | E107: Dynamics | F107: CCS PST China | H107: =IFERROR(VLOOKUP(Table3[[#This Row],[SF Assignment Group Name]],'Assignment Group Usage'!B:D,3,FALSE),0) -> 65
A108: SFDC Handup | B108: PL Connectivity Group | C108: Yes | D108: Jason | E108: Dynamics | F108: CCS PST Connectivity | H108: =IFERROR(VLOOKUP(Table3[[#This Row],[SF Assignment Group Name]],'Assignment Group Usage'!B:D,3,FALSE),0) -> 137
A109: SFDC Handup | B109: PST Group | C109: Yes | E109: Dynamics | F109: CCS PST Digital | H109: =IFERROR(VLOOKUP(Table3[[#This Row],[SF Assignment Group Name]],'Assignment Group Usage'!B:D,3,FALSE),0) -> 1740
A110: SFDC Handup | B110: CCS T2 - ECS Group | C110: Yes | D110: Darren | E110: Dynamics | F110: CCS PST ECS | G110: Concentrix | H110: =IFERROR(VLOOKUP(Table3[[#This Row],[SF Assignment Group Name]],'Assignment Group Usage'!B:D,3,FALSE),0) -> 2
C111: Yes | E111: Dynamics | F111: CCS PST Empower | H111: =IFERROR(VLOOKUP(Table3[[#This Row],[SF Assignment Group Name]],'Assignment Group Usage'!B:D,3,FALSE),0) -> 0
A112: SFDC Handup | B112: CCS T2 - ETS Group | C112: Yes | D112: Sarah | E112: Dynamics | F112: CCS PST ETS | H112: =IFERROR(VLOOKUP(Table3[[#This Row],[SF Assignment Group Name]],'Assignment Group Usage'!B:D,3,FALSE),0) -> 1
C113: Yes | E113: Dynamics | F113: CCS PST M&T | H113: =IFERROR(VLOOKUP(Table3[[#This Row],[SF Assignment Group Name]],'Assignment Group Usage'!B:D,3,FALSE),0) -> 0
A114: SFDC Handup | B114: Remote Fleet Vision Tier 2 Group | C114: Yes | D114: Jason | E114: Dynamics | F114: RFV T2 | H114: =IFERROR(VLOOKUP(Table3[[#This Row],[SF Assignment Group Name]],'Assignment Group Usage'!B:D,3,FALSE),0) -> 40
C115: Yes | E115: Dynamics | F115: CCS SE Digital | H115: =IFERROR(VLOOKUP(Table3[[#This Row],[SF Assignment Group Name]],'Assignment Group Usage'!B:D,3,FALSE),0) -> 0
A116: SFDC Handup | B116: Empower Group | C116: Yes | D116: Carita | E116: Dynamics | F116: CCS SE Empower | H116: =IFERROR(VLOOKUP(Table3[[#This Row],[SF Assignment Group Name]],'Assignment Group Usage'!B:D,3,FALSE),0) -> 19
A117: SFDC Handup | B117: Cat Rental Internal Group | C117: Yes | D117: Stacy / Julia | E117: Dynamics | F117: CCS SE Rental | H117: =IFERROR(VLOOKUP(Table3[[#This Row],[SF Assignment Group Name]],'Assignment Group Usage'!B:D,3,FALSE),0) -> 20
A118: Manual Handup | B118: Service Letter Group | C118: Yes | D118: Jason | E118: Dynamics | F118: Service Letter | H118: =IFERROR(VLOOKUP(Table3[[#This Row],[SF Assignment Group Name]],'Assignment Group Usage'!B:D,3,FALSE),0) -> 1
A119: SFDC Handup | B119: SpecSizer Group | C119: Yes | D119: Carita / Lauren | E119: Dynamics | F119: SpecSizer | H119: =IFERROR(VLOOKUP(Table3[[#This Row],[SF Assignment Group Name]],'Assignment Group Usage'!B:D,3,FALSE),0) -> 24
A120: SFDC Handup | B120: STU Product Group | C120: Yes | D120: Kath | E120: Dynamics | F120: STU Product | H120: =IFERROR(VLOOKUP(Table3[[#This Row],[SF Assignment Group Name]],'Assignment Group Usage'!B:D,3,FALSE),0) -> 3
A121: SFDC Handup | B121: VIMS Engineering Group | C121: Yes | D121: Jason | E121: Dynamics | F121: VIMS Engineering | H121: =IFERROR(VLOOKUP(Table3[[#This Row],[SF Assignment Group Name]],'Assignment Group Usage'!B:D,3,FALSE),0) -> 13
A122: SFDC Handup | B122: HEI/VLP Group | C122: Yes | D122: Jason | E122: Dynamics | F122: VisionLink Productivity | G122: Retiring - do we need? | H122: =IFERROR(VLOOKUP(Table3[[#This Row],[SF Assignment Group Name]],'Assignment Group Usage'!B:D,3,FALSE),0) -> 143
A123: SFDC Handup | B123: VL Tier 2 Group | C123: Yes | D123: Lauren | E123: Dynamics | F123: VL Tier 2 | H123: =IFERROR(VLOOKUP(Table3[[#This Row],[SF Assignment Group Name]],'Assignment Group Usage'!B:D,3,FALSE),0) -> 237
A124: Manual Handup | B124: Other Group | C124: Yes | D124: Kath | E124: Manual | F124: Other Group | H124: =IFERROR(VLOOKUP(Table3[[#This Row],[SF Assignment Group Name]],'Assignment Group Usage'!B:D,3,FALSE),0) -> 261
A125: SFDC Handup | B125: Parts Expert Group | C125: No | D125: Darren | F125: Retired | G125: Check with Darren | H125: =IFERROR(VLOOKUP(Table3[[#This Row],[SF Assignment Group Name]],'Assignment Group Usage'!B:D,3,FALSE),0) -> 10
A126: SFDC Handup | B126: eCommerce Group | C126: Yes | D126: Sarah | E126: Dynamics | F126: CCS SE ECS | H126: =IFERROR(VLOOKUP(Table3[[#This Row],[SF Assignment Group Name]],'Assignment Group Usage'!B:D,3,FALSE),0) -> 24
C127: Yes | E127: Dynamics | F127: CCS SE ETS | H127: =IFERROR(VLOOKUP(Table3[[#This Row],[SF Assignment Group Name]],'Assignment Group Usage'!B:D,3,FALSE),0) -> 0
A128: SFDC Handup | B128: Cat Interact Group | D128: Carita / Lauren | H128: =IFERROR(VLOOKUP(Table3[[#This Row],[SF Assignment Group Name]],'Assignment Group Usage'!B:D,3,FALSE),0) -> 38
A129: Manual Handup | B129: Anchnet Group | H129: =IFERROR(VLOOKUP(Table3[[#This Row],[SF Assignment Group Name]],'Assignment Group Usage'!B:D,3,FALSE),0) -> 19
A130: SFDC Handup | B130: Concentrix China Team Leader Group | H130: =IFERROR(VLOOKUP(Table3[[#This Row],[SF Assignment Group Name]],'Assignment Group Usage'!B:D,3,FALSE),0) -> 3
A131: SFDC Handup | B131: RFV Sales & Education Group | H131: =IFERROR(VLOOKUP(Table3[[#This Row],[SF Assignment Group Name]],'Assignment Group Usage'!B:D,3,FALSE),0) -> 3
A132: SFDC Handup | B132: PLE- Data Streaming Group | H132: =IFERROR(VLOOKUP(Table3[[#This Row],[SF Assignment Group Name]],'Assignment Group Usage'!B:D,3,FALSE),0) -> 2
A133: SFDC Handup | B133: Service Letter Group | C133: No | F133: Retired | G133: why manual and sf | H133: =IFERROR(VLOOKUP(Table3[[#This Row],[SF Assignment Group Name]],'Assignment Group Usage'!B:D,3,FALSE),0) -> 1
A134: Manual Handup | B134: SEM China Group | H134: =IFERROR(VLOOKUP(Table3[[#This Row],[SF Assignment Group Name]],'Assignment Group Usage'!B:D,3,FALSE),0) -> 1
A135: SFDC Handup | B135: Targeted Connectivity Dashboard Group | D135: Carita / Lauren | H135: =IFERROR(VLOOKUP(Table3[[#This Row],[SF Assignment Group Name]],'Assignment Group Usage'!B:D,3,FALSE),0) -> 1

Sheet CCS Assignment Groups
A1: First Name | B1: Last Name | C1: Assignment Group | D1: Who | E1: Manager
A2: Noah | B2: Rolan | C2: PST Connectivity | D2: Cat | E2: Don Kern
A3: Robert | B3: Hanks | C3: PST Connectivity | D3: Cat | E3: Don Kern
A4: Christian | B4: Merrick | C4: PST Connectivity | D4: Cat | E4: Don Kern
A5: Thomas | B5: Fisher | C5: PST Connectivity | D5: Cat | E5: Don Kern
A6: Michael | B6: Larsen | C6: PST Connectivity | D6: Cat | E6: Don Kern
A7: Brandon | B7: Snead | C7: PST Connectivity | D7: Cat | E7: Don Kern
A8: Kaiden | B8: Love | C8: PST Connectivity | D8: Cat | E8: Don Kern
A9: Marlon | B9: Ball | C9: PST Connectivity | D9: Cat | E9: Don Kern
A10: Tyler | B10: Hasty | C10: PST Connectivity | D10: Cat | E10: Don Kern
A11: John | B11: Ciko | C11: PST Digital | D11: Cat | E11: Jeff Sharp
A12: Jim | B12: Craig | C12: PST Digital | D12: Cat | E12: Jeff Sharp
... A58: James | B58: Alderson | C58: PST M&T | D58: Cat | E58: Sherri Schmidt
C59: CCS DAS Analytics | E59: Derek Blunier
C60: CCS DAS Analytics | E60: Derek Blunier
C61: CCS DAS Analytics | E61: Derek Blunier
C62: CCS DAS Analytics | E62: Derek Blunier
C63: CCS DAS Analytics | E63: Derek Blunier

Sheet T2 Assignment Groups Names
A1: Assignment Group | B1: Manager | C1: First Name | D1: Last Name

Sheet Projects

Sheet Assignment Group Usage
A1: Assignment Group: Type ↑ | B1: Assignment Group Name ↑ | C1: Handup: Created Date ↑ | D1: Record Count
A2: Manual Handup | B2: Anchnet Group | C2: January 2025 | D2: 19 | G2: Assignment Group Counts
C3: February 2025 | D3: 13 | G3: As of 2026-09-01 20:32:19 Central Standard Time/CST • Generated by Tiffani Potter
C4: March 2025 | D4: 50
C5: April 2025 | D5: 33
C6: May 2025 | D6: 51 | G6: Filtered By
C7: June 2025 | D7: 45 | G7: Show: All handups
C8: July 2025 | D8: 59 | G8: Date Field: Handup Created Date equals Current and Previous FY (1/1/2025 to 12/31/2026)
C9: August 2025 | D9: 45
C10: September 2025 | D10: 49
C11: October 2025 | D11: 17
C12: November 2025 | D12: 24
C13: December 2025 | D13: 34
C14: January 2026 | D14: 34
C15: February 2026 | D15: 17
C16: March 2026 | D16: 56
C17: April 2026 | D17: 45
C18: May 2026 | D18: 20
C19: June 2026 | D19: 40
C20: July 2026 | D20: 48
... C22: September 2026 | D22: 3
B23: API Group | C23: March 2025 | D23: 7
C24: April 2025 | D24: 3
C25: May 2025 | D25: 6
C26: June 2025 | D26: 2
C27: July 2025 | D27: 5
C28: October 2025 | D28: 3
C29: December 2025 | D29: 4
C30: January 2026 | D30: 1
C31: February 2026 | D31: 1
C32: March 2026 | D32: 3
C33: May 2026 | D33: 4
C34: June 2026 | D34: 3
C35: July 2026 | D35: 2
C36: August 2026 | D36: 1
B37: BaaS Tier 2 Group | C37: March 2025 | D37: 1
B38: Billing Group | C38: January 2025 | D38: 14
C39: February 2025 | D39: 28
C40: March 2025 | D40: 27
C41: April 2025 | D41: 29
C42: May 2025 | D42: 17
C43: June 2025 | D43: 17
C44: July 2025 | D44: 13
C45: August 2025 | D45: 11
C46: September 2025 | D46: 13
C47: October 2025 | D47: 14
C48: November 2025 | D48: 12
C49: December 2025 | D49: 9
C50: January 2026 | D50: 15
... C57: August 2026 | D57: 7
B58: Bulk CCID Creation Group | C58: November 2025 | D58: 3
C59: December 2025 | D59: 2
C60: February 2026 | D60: 2
C61: March 2026 | D61: 17
C62: April 2026 | D62: 11
C63: May 2026 | D63: 9
C64: June 2026 | D64: 5
C65: July 2026 | D65: 11
C66: August 2026 | D66: 18
C67: September 2026 | D67: 2
B68: Cat Central Group | C68: January 2025 | D68: 1
C69: February 2025 | D69: 1
C70: March 2025 | D70: 1
C71: April 2025 | D71: 2
C72: May 2025 | D72: 4
C73: August 2025 | D73: 2
C74: September 2025 | D74: 4
C75: October 2025 | D75: 2
C76: November 2025 | D76: 4
B77: Cat Foresight Group | C77: January 2025 | D77: 88
C78: February 2025 | D78: 66
C79: March 2025 | D79: 81
C80: April 2025 | D80: 70
C81: May 2025 | D81: 114
C82: June 2025 | D82: 60
C83: July 2025 | D83: 87
C84: August 2025 | D84: 72
C85: September 2025 | D85: 105
C86: October 2025 | D86: 86
C87: November 2025 | D87: 49
C88: December 2025 | D88: 37
C89: January 2026 | D89: 38
... C97: September 2026 | D97: 2
B98: Cat Inspect API Approval Group | C98: February 2025 | D98: 1
C99: May 2025 | D99: 2
C100: June 2025 | D100: 2
B101: Cat Inspect Group | C101: January 2025 | D101: 1
C102: April 2025 | D102: 1
C103: June 2025 | D103: 2
C104: July 2025 | D104: 3
C105: August 2025 | D105: 1
C106: November 2025 | D106: 4
C107: December 2025 | D107: 1
C108: March 2026 | D108: 1
C109: July 2026 | D109: 1
B110: Customer Admin Tool Group | C110: January 2025 | D110: 1
C111: February 2025 | D111: 4
C112: March 2025 | D112: 5
C113: April 2025 | D113: 7
C114: May 2025 | D114: 17
...
